{
  "kind": "collectionType",
  "collectionName": "categories",
  "info": {
    "name": "category",
    "description": ""
  },
  "options": {
    "increments": true,
    "timestamps": true,
    "draftAndPublish": true
  },
  "pluginOptions": {},
  "attributes": {
    "name": {
      "type": "string"
    },
    "products": {
      "via": "categories",
      "collection": "product"
    },
    "men": {
      "collection": "men",
      "via": "categories",
      "dominant": true
    },
    "women": {
      "collection": "women",
      "via": "categories",
      "dominant": true
    },
    "boys": {
      "collection": "boys",
      "via": "categories",
      "dominant": true
    },
    "girls": {
      "collection": "girls",
      "via": "categories",
      "dominant": true
    }
  }
}
